vrd/__init__.py
vrd/annotation_matcher.py
vrd/dbhandler.py
vrd/faiss_helper.py
vrd/frame_extractor.py
vrd/image_preprocessing.py
vrd/keras_layer_helper.py
vrd/neighbours.py
vrd/neural_networks.py
vrd/notebook_helper.py
vrd/overlap_calculator.py
vrd/sequence_finder.py
vrd/vrd_project.py
vrd/widgets/__init__.py
vrd/widgets/manual_image_preview.py
vrd/widgets/sequences_w_lowest_distance_by_duration.py
vrd/widgets/sequences_w_lowest_distances.py
video_reuse_detector-0.1.4.dist-info/METADATA
video_reuse_detector-0.1.4.dist-info/WHEEL
video_reuse_detector-0.1.4.dist-info/RECORD
